[ { "id": "148501", "title": "CLASSIC GAME", "added": 1731173398851, "platform": 2, "uri": "https://iamqqqqqqq.itch.io/classicgame", "tags": [ ], "archived": false }, { "id": "277022", "title": "HOME GAME", "added": 1731173398851, "platform": 2, "uri": "https://iamqqqqqqq.itch.io/homegame", "tags": [ ], "archived": false }, { "id": "312054", "title": "Clean ATTACK!", "added": 1731173398851, "platform": 2, "uri": "https://diadas.itch.io/clean-attack", "tags": [ ], "archived": false }, { "id": "316515", "title": "Thermo Puzzle", "added": 1731173398851, "platform": 2, "uri": "https://diadas.itch.io/thermo-game", "tags": [ ], "archived": false }, { "id": "322073", "title": "Sky Lab Defender", "added": 1731173398851, "platform": 2, "uri": "https://kasperv.itch.io/skylabdefender", "tags": [ ], "archived": false }, { "id": "466381", "title": "GRAVITY Pilot!", "added": 1731173398851, "platform": 2, "uri": "https://diadas.itch.io/gravity-pilot", "tags": [ ], "archived": false }, { "id": "557873", "title": "HOME GAME 2", "added": 1731173398851, "platform": 2, "uri": "https://iamqqqqqqq.itch.io/homegame2", "tags": [ ], "archived": false }, { "id": "590548", "title": "Juice Galaxy (formerly Juice World)", "added": 1731173398851, "platform": 2, "uri": "https://fishlicka.itch.io/juice-galaxy", "tags": [ ], "archived": false }, { "id": "662059", "title": "Evolvedustry", "added": 1731173398851, "platform": 2, "uri": "https://evolvedustry.itch.io/evolvedustry", "tags": [ ], "archived": false }, { "id": "808649", "title": "Asteroids", "added": 1731173398851, "platform": 2, "uri": "https://magnus-froelund.itch.io/asteroids", "tags": [ ], "archived": false }, { "id": "844771", "title": "Stargates", "added": 1731173398851, "platform": 2, "uri": "https://magnus-froelund.itch.io/stargates", "tags": [ ], "archived": false }, { "id": "884968", "title": "1943", "added": 1731173398851, "platform": 2, "uri": "https://magnus-froelund.itch.io/1943", "tags": [ ], "archived": false }, { "id": "885042", "title": "5 in 1 Retro Games", "added": 1731173398851, "platform": 2, "uri": "https://magnus-froelund.itch.io/5-in-1-retro-games", "tags": [ ], "archived": false }, { "id": "999235", "title": "Larger Than Light", "added": 1731173398851, "platform": 2, "uri": "https://1010meha.itch.io/larger-than-light", "tags": [ ], "archived": false }, { "id": "1089552", "title": "Omega No Sunshine 24", "added": 1731173398851, "platform": 2, "uri": "https://galoxyum.itch.io/ons24", "tags": [ ], "archived": false }, { "id": "1232335", "title": "Капитал Шоу + Супер Игра", "added": 1731173398851, "platform": 2, "uri": "https://existical.itch.io/capitalshow", "tags": [ ], "archived": false }, { "id": "1408299", "title": "The Labyrinth of Kur", "added": 1731173398851, "platform": 2, "uri": "https://fontty.itch.io/kur", "tags": [ ], "archived": false }, { "id": "1551687", "title": "The Simple Life", "added": 1731173398851, "platform": 2, "uri": "https://kasperv.itch.io/the-simple-life", "tags": [ ], "archived": false }, { "id": "1581097", "title": "Ball Down Hill", "added": 1731173398851, "platform": 2, "uri": "https://kasperv.itch.io/ball-down-hill", "tags": [ ], "archived": false }, { "id": "1647834", "title": "The backrooms: Uncovered", "added": 1731173398851, "platform": 2, "uri": "https://magnus-froelund.itch.io/the-backrooms", "tags": [ ], "archived": false }, { "id": "1651086", "title": "Forgotten Cowboys", "added": 1731173398851, "platform": 2, "uri": "https://musialkov.itch.io/forgotten-cobwoys", "tags": [ ], "archived": false }, { "id": "1665362", "title": "Ancient Evil", "added": 1731173398851, "platform": 2, "uri": "https://musialkov.itch.io/ancient-evil", "tags": [ ], "archived": false }, { "id": "1710220", "title": "Oddworld: Smile Factory", "added": 1731173398851, "platform": 2, "uri": "https://pupbenny.itch.io/oddworld", "tags": [ ], "archived": false }, { "id": "1750560", "title": "Basic Shooter (Pre Alpha)", "added": 1731173398851, "platform": 2, "uri": "https://magnus-froelund.itch.io/campers-killers-pre-alpha", "tags": [ ], "archived": false }, { "id": "1805021", "title": "Endless Math Challenge", "added": 1731173398851, "platform": 2, "uri": "https://notritter.itch.io/endless-math-challenge", "tags": [ ], "archived": false }, { "id": "1924864", "title": "House Cleaner", "added": 1731173398851, "platform": 2, "uri": "https://al7ussain.itch.io/housecleaner", "tags": [ ], "archived": false }, { "id": "1925836", "title": "Are you There?", "added": 1731173398851, "platform": 2, "uri": "https://magnus-froelund.itch.io/are-you-there", "tags": [ ], "archived": false }, { "id": "2058788", "title": "The Lost Apartment Demo", "added": 1731173398851, "platform": 2, "uri": "https://sdevscares.itch.io/the-lost-apartment", "tags": [ ], "archived": false }, { "id": "2100322", "title": "Kasperias Arenas", "added": 1731173398851, "platform": 2, "uri": "https://kasperv.itch.io/kasperias-arenas", "tags": [ ], "archived": false }, { "id": "2117009", "title": "Puzzle Box Island", "added": 1731173398851, "platform": 2, "uri": "https://puzzle-box-island.itch.io/puzzle-box-island", "tags": [ ], "archived": false }, { "id": "2173549", "title": "Pigeon West: Johnny the Pigeon", "added": 1731173398851, "platform": 2, "uri": "https://squidsquadpapi.itch.io/johnny-the-pigeon", "tags": [ ], "archived": false }, { "id": "2176424", "title": "Desktop Car", "added": 1731173398851, "platform": 2, "uri": "https://magnus-froelund.itch.io/desktop-car", "tags": [ ], "archived": false }, { "id": "2179309", "title": "Between two Worlds - Family Day", "added": 1731173398851, "platform": 2, "uri": "https://pixelpun.itch.io/betweentwoworldsfamilyday", "tags": [ ], "archived": false }, { "id": "2200835", "title": "Red Tail", "added": 1731173398851, "platform": 2, "uri": "https://musialkov.itch.io/redtail", "tags": [ ], "archived": false }, { "id": "2211539", "title": "The Drifters", "added": 1731173398851, "platform": 2, "uri": "https://magnus-froelund.itch.io/the-drifters", "tags": [ ], "archived": false }, { "id": "2215788", "title": "Quiet West: Butcher noose", "added": 1731173398851, "platform": 2, "uri": "https://squidsquadpapi.itch.io/quiet-west-butcher-noose", "tags": [ ], "archived": false }, { "id": "2217520", "title": "Foxy Man", "added": 1731173398851, "platform": 2, "uri": "https://al7ussain.itch.io/foxy-man", "tags": [ ], "archived": false }, { "id": "2223223", "title": "House Cleaner 2", "added": 1731173398851, "platform": 2, "uri": "https://al7ussain.itch.io/house-cleaner-2", "tags": [ ], "archived": false }, { "id": "2230133", "title": "Maze", "added": 1731173398851, "platform": 2, "uri": "https://al7ussain.itch.io/maze", "tags": [ ], "archived": false }, { "id": "2237185", "title": "Simple Tasks", "added": 1731173398851, "platform": 2, "uri": "https://al7ussain.itch.io/simple-tasks", "tags": [ ], "archived": false }, { "id": "2242326", "title": "Zombie Hunter", "added": 1731173398851, "platform": 2, "uri": "https://al7ussain.itch.io/zombie-hunter", "tags": [ ], "archived": false }, { "id": "2300883", "title": "Here We Go Again", "added": 1731173398851, "platform": 2, "uri": "https://al7ussain.itch.io/hear-we-go-again", "tags": [ ], "archived": false }, { "id": "2303271", "title": "Cubic Void", "added": 1731173398851, "platform": 2, "uri": "https://blobbyweirdthing.itch.io/cubic-void", "tags": [ ], "archived": false }, { "id": "2306199", "title": "UnrealityDread", "added": 1731173398851, "platform": 2, "uri": "https://sdevscares.itch.io/unreality-dread", "tags": [ ], "archived": false }, { "id": "2312843", "title": "One Spike", "added": 1731173398851, "platform": 2, "uri": "https://al7ussain.itch.io/one-spike", "tags": [ ], "archived": false }, { "id": "2372845", "title": "Armored Crucible: The Crimson Dunes", "added": 1731173398851, "platform": 2, "uri": "https://fontty.itch.io/ac-tcd", "tags": [ ], "archived": false }, { "id": "2372918", "title": "The Cropping Night", "added": 1731173398851, "platform": 2, "uri": "https://onequidgames.itch.io/the-cropping-night", "tags": [ ], "archived": false }, { "id": "2445604", "title": "Untitled Gore Game", "added": 1731173398851, "platform": 2, "uri": "https://magnus-froelund.itch.io/untitled-gore-game", "tags": [ ], "archived": false }, { "id": "2474952", "title": "How my Brain Works", "added": 1731173398851, "platform": 2, "uri": "https://blobbyweirdthing.itch.io/how-my-brain-works", "tags": [ ], "archived": false }, { "id": "2511349", "title": "Very bad Flappy Bird", "added": 1731173398851, "platform": 2, "uri": "https://blobbyweirdthing.itch.io/very-bad-flappy-bird", "tags": [ ], "archived": false }, { "id": "2536397", "title": "Daunting", "added": 1731173398851, "platform": 2, "uri": "https://sdevscares.itch.io/daunting", "tags": [ ], "archived": false }, { "id": "2577979", "title": "Beanman", "added": 1731173398851, "platform": 2, "uri": "https://archimedean-gaming.itch.io/beanman", "tags": [ ], "archived": false }, { "id": "2590002", "title": "Pigeon West: El Diablo", "added": 1731173398851, "platform": 2, "uri": "https://squidsquadpapi.itch.io/pigeon-west-el-diablo", "tags": [ ], "archived": false }, { "id": "2603177", "title": "Cubic Void WebGL (Broken)", "added": 1731173398851, "platform": 2, "uri": "https://blobbyweirdthing.itch.io/cubic-void-webgl", "tags": [ ], "archived": false }, { "id": "2710690", "title": "Jungle Jumper", "added": 1731173398851, "platform": 2, "uri": "https://adamnn.itch.io/jungle-jumpertt", "tags": [ ], "archived": false }, { "id": "2714536", "title": "Tiny Tails: The Whale’s Tale", "added": 1731173398851, "platform": 2, "uri": "https://al7ussain.itch.io/whale-game", "tags": [ ], "archived": false }, { "id": "2729656", "title": "War of Ants!", "added": 1731173398851, "platform": 2, "uri": "https://15joldersmat.itch.io/ants", "tags": [ ], "archived": false }, { "id": "2733321", "title": "Fear the light", "added": 1731173398851, "platform": 2, "uri": "https://tomython.itch.io/fear-the-light", "tags": [ ], "archived": false }, { "id": "2781453", "title": "V.H.S", "added": 1731173398851, "platform": 2, "uri": "https://alexbaza.itch.io/vhs", "tags": [ ], "archived": false }, { "id": "2785303", "title": "V.H.S: Chapter 2", "added": 1731173398851, "platform": 2, "uri": "https://alexbaza.itch.io/vhs-chapter-2", "tags": [ ], "archived": false }, { "id": "2785469", "title": "Minimperiums", "added": 1731173398851, "platform": 2, "uri": "https://15joldersmat.itch.io/minimperiums", "tags": [ ], "archived": false }, { "id": "2813517", "title": "V.H.S: Remastered", "added": 1731173398851, "platform": 2, "uri": "https://alexbaza.itch.io/vhs-remastered", "tags": [ ], "archived": false }, { "id": "2816104", "title": "Extracted", "added": 1731173398851, "platform": 2, "uri": "https://warlines.itch.io/extracted", "tags": [ ], "archived": false }, { "id": "2816735", "title": "V.H.S Chapter 2: Remastered", "added": 1731173398851, "platform": 2, "uri": "https://alexbaza.itch.io/vhs-chapter-2-remastered", "tags": [ ], "archived": false }, { "id": "2817442", "title": "Evidence of 96'", "added": 1731173398851, "platform": 2, "uri": "https://teammelon.itch.io/evidence-of-96", "tags": [ ], "archived": false }, { "id": "2817852", "title": "Orbital Empires", "added": 1731173398851, "platform": 2, "uri": "https://15joldersmat.itch.io/orbital-empires", "tags": [ ], "archived": false }, { "id": "2829988", "title": "Please Remember Me!", "added": 1731173398851, "platform": 2, "uri": "https://jjbeats99.itch.io/please-remember-me", "tags": [ ], "archived": false }, { "id": "2840189", "title": "Dead Coliseum", "added": 1731173398851, "platform": 2, "uri": "https://alexbaza.itch.io/coliseum", "tags": [ ], "archived": false }, { "id": "2911449", "title": "A Date to Remember", "added": 1731173398851, "platform": 2, "uri": "https://jjbeats99.itch.io/a-date-to-remember", "tags": [ ], "archived": false }, { "id": "2918111", "title": "The Burrow", "added": 1731173398851, "platform": 2, "uri": "https://saladin786.itch.io/the-burrow", "tags": [ ], "archived": false }, { "id": "2924781", "title": "The Quest for the Loot", "added": 1731173398851, "platform": 2, "uri": "https://jjbeats99.itch.io/the-quest-for-the-loot", "tags": [ ], "archived": false }, { "id": "2934727", "title": "JJBEATS GAMING", "added": 1731173398851, "platform": 2, "uri": "https://jjbeats99.itch.io/jjbeats-gaming", "tags": [ ], "archived": false }, { "id": "2935821", "title": "Sheris Dungeon: PROTECT THE BALLS", "added": 1731173398851, "platform": 2, "uri": "https://kittycreampuff.itch.io/sd", "tags": [ ], "archived": false }, { "id": "2936717", "title": "The Whitaker's Library", "added": 1731173398851, "platform": 2, "uri": "https://lorex-games.itch.io/the-whitakers-library-part-1", "tags": [ ], "archived": false }, { "id": "2959441", "title": "Kookie", "added": 1731173398851, "platform": 2, "uri": "https://jjbeats99.itch.io/kookie", "tags": [ ], "archived": false }, { "id": "2964192", "title": "Stalker", "added": 1731173398851, "platform": 2, "uri": "https://gamingtgt.itch.io/stalker", "tags": [ ], "archived": false }, { "id": "2964719", "title": "A Dandy Election (Election Sim)", "added": 1731173398851, "platform": 2, "uri": "https://15joldersmat.itch.io/a-dandy-election", "tags": [ ], "archived": false }, { "id": "2967173", "title": "Ball 46", "added": 1731173398851, "platform": 2, "uri": "https://yahay-games.itch.io/ball-46", "tags": [ ], "archived": false }, { "id": "2989130", "title": "Their Navy Is Their Doom", "added": 1731173398851, "platform": 2, "uri": "https://pressfstudio.itch.io/their-navy-is-their-doom", "tags": [ ], "archived": false }, { "id": "3034996", "title": "Christmas Kids", "added": 1731173398851, "platform": 2, "uri": "https://alexbaza.itch.io/christmas-kids", "tags": [ ], "archived": false }, { "id": "3041323", "title": "Being Stalked", "added": 1731173398851, "platform": 2, "uri": "https://gamingtgt.itch.io/being-stalked", "tags": [ ], "archived": false }, { "id": "3045718", "title": "Fabric", "added": 1731173398851, "platform": 2, "uri": "https://alexbaza.itch.io/fabric", "tags": [ ], "archived": false }, { "id": "3051359", "title": "Rise Above!", "added": 1731173398851, "platform": 2, "uri": "https://alessandro06-0.itch.io/rise-above", "tags": [ ], "archived": false }, { "id": "3057443", "title": "The Parking", "added": 1731173398851, "platform": 2, "uri": "https://gamingtgt.itch.io/the-parking", "tags": [ ], "archived": false }, { "id": "3070433", "title": "JACKER", "added": 1731173398851, "platform": 2, "uri": "https://ry2110.itch.io/jacker", "tags": [ ], "archived": false }, { "id": "3075880", "title": "Fabric: Chapter 2", "added": 1731173398851, "platform": 2, "uri": "https://alexbaza.itch.io/fabric-chapter-2", "tags": [ ], "archived": false }, { "id": "3081113", "title": "MAD? FROGG - Multiplayer PVP", "added": 1731173398851, "platform": 2, "uri": "https://pumpp-studios.itch.io/madfrogg", "tags": [ ], "archived": false }, { "id": "3088964", "title": "FragmentsOfTyranny(Demo)", "added": 1731173398851, "platform": 2, "uri": "https://khoyman.itch.io/fragmentsoftyrannydemo", "tags": [ ], "archived": false }, { "id": "3093113", "title": "flappy effects", "added": 1731173398851, "platform": 2, "uri": "https://alessandro06-0.itch.io/flappy-effects", "tags": [ ], "archived": false }, { "id": "3101615", "title": "Proster", "added": 1731173398851, "platform": 2, "uri": "https://rtvr5656.itch.io/proster", "tags": [ ], "archived": false }, { "id": "3105595", "title": "The Lost Arctic", "added": 1731173398851, "platform": 2, "uri": "https://puzzle-box-island.itch.io/the-lost-arctic", "tags": [ ], "archived": false }, { "id": "2981812", "title": "Block Run 1000", "added": 1731919319346, "platform": 2, "uri": "https://dreamerkid.itch.io/block-run", "tags": [ ], "archived": false }, { "id": "3039786", "title": "STAaRS", "added": 1731919319346, "platform": 2, "uri": "https://ayfjay.itch.io/staars", "tags": [ ], "archived": false }, { "id": "750499", "title": "Roses Of Love", "added": 1732001794835, "platform": 2, "uri": "https://kagarisoft.itch.io/rol", "tags": [ ], "archived": false }, { "id": "1316240", "title": "THE WHOLE WORLD", "added": 1732001794835, "platform": 2, "uri": "https://gwa123.itch.io/the-whole-world", "tags": [ ], "archived": false }, { "id": "1326785", "title": "SUD GAME", "added": 1732001794835, "platform": 2, "uri": "https://gwa123.itch.io/sud-game", "tags": [ ], "archived": false }, { "id": "1647166", "title": "Name The Pokemon", "added": 1732001794835, "platform": 2, "uri": "https://gwa123.itch.io/name-the-pokemon", "tags": [ ], "archived": false }, { "id": "1715054", "title": "DEAR NIGHT", "added": 1732001794835, "platform": 2, "uri": "https://gwa123.itch.io/dear-night", "tags": [ ], "archived": false }, { "id": "1719334", "title": "Its Time To Fight", "added": 1732001794835, "platform": 2, "uri": "https://gwa123.itch.io/its-time-to-fight", "tags": [ ], "archived": false }, { "id": "1720746", "title": "Battleground Powers", "added": 1732001794835, "platform": 2, "uri": "https://gwa123.itch.io/battleground-powers", "tags": [ ], "archived": false }, { "id": "1726967", "title": "Theme Park Tycoon", "added": 1732001794835, "platform": 2, "uri": "https://gwa123.itch.io/theme-park-tycoon", "tags": [ ], "archived": false }, { "id": "1728413", "title": "Basketball", "added": 1732001794835, "platform": 2, "uri": "https://gwa123.itch.io/football", "tags": [ ], "archived": false }, { "id": "1732498", "title": "Brawl Star Simulator", "added": 1732001794835, "platform": 2, "uri": "https://gwa123.itch.io/brawl-star-simulator", "tags": [ ], "archived": false }, { "id": "1732582", "title": "Zizzy Zombie", "added": 1732001794835, "platform": 2, "uri": "https://gwa123.itch.io/zizzy-zombie", "tags": [ ], "archived": false }, { "id": "1735429", "title": "Fight With Assassination Creed", "added": 1732001794835, "platform": 2, "uri": "https://gwa123.itch.io/fight-with-assassi", "tags": [ ], "archived": false }, { "id": "1743345", "title": "Champion", "added": 1732001794835, "platform": 2, "uri": "https://gwa123.itch.io/champion", "tags": [ ], "archived": false }, { "id": "1839497", "title": "Doctor Abhas", "added": 1732001794835, "platform": 2, "uri": "https://gwa123.itch.io/doctor-abhas", "tags": [ ], "archived": false }, { "id": "2199811", "title": "Sherlock Holmes and The Secret Weapon for Commodore 64", "added": 1732001794835, "platform": 2, "uri": "https://zartan917.itch.io/sherlock-holmes-and-the-secret-weapon-for-commodore-64", "tags": [ ], "archived": false }, { "id": "2243634", "title": "Pass Problems for PLAYDATE", "added": 1732001794835, "platform": 2, "uri": "https://zartan917.itch.io/pass-problems-for-playdate", "tags": [ ], "archived": false }, { "id": "2257162", "title": "Americannon Civil War Sokoban for NES", "added": 1732001794835, "platform": 2, "uri": "https://zartan917.itch.io/americannon", "tags": [ ], "archived": false }, { "id": "2611946", "title": "Boke", "added": 1732001794835, "platform": 2, "uri": "https://gwa123.itch.io/boke", "tags": [ ], "archived": false }, { "id": "2790289", "title": "Make Money Simulation", "added": 1732001794835, "platform": 2, "uri": "https://gwa123.itch.io/make-money-simulation", "tags": [ ], "archived": false }, { "id": "2980313", "title": "Battle Hell: Tral!", "added": 1732001794835, "platform": 2, "uri": "https://15joldersmat.itch.io/battle-hell-tral", "tags": [ ], "archived": false }, { "id": "3033194", "title": "Wawi's Mod 3", "added": 1732001794835, "platform": 2, "uri": "https://mundoraroxd.itch.io/wawis-mod-3", "tags": [ ], "archived": false }, { "id": "3116448", "title": "Beep Sheep Simulator", "added": 1732001794835, "platform": 2, "uri": "https://osamamsa123.itch.io/beep-sheep-simulator", "tags": [ ], "archived": false }, { "id": "3117049", "title": "Get Free W.I.P", "added": 1732001794835, "platform": 2, "uri": "https://kunai-studios.itch.io/get-free-wip", "tags": [ ], "archived": false }, { "id": "fddca2297b9a4354b59f8f83d4975c90", "title": "Snakebird Complete", "added": 1731173398853, "platform": 4, "uri": "https://store.epicgames.com/en-US/p/snakebird-complete-e6f0ae", "tags": [ ], "archived": false }, { "id": "8f80897c0b6e4e678fed08da169d44be", "title": "Castlevania Anniversary Collection", "added": 1731173398853, "platform": 4, "uri": "https://store.epicgames.com/en-US/p/castlevania-anniversary-collection-a61f94", "tags": [ ], "archived": false }, { "id": "9nbx3zg9zz8j", "title": "Flight Masters: The Horizon Chase", "added": 1731173398872, "platform": 5, "uri": "https://apps.microsoft.com/detail/9nbx3zg9zz8j", "tags": [ ], "archived": false }, { "id": "9nwzwmqt3410", "title": "Tetromino Zen", "added": 1731173398872, "platform": 5, "uri": "https://apps.microsoft.com/detail/9nwzwmqt3410", "tags": [ ], "archived": false }, { "id": "10005940", "title": "Hotline Miami", "added": 1732001827084, "platform": 9, "uri": "https://store.playstation.com/en-us/concept/10005940", "tags": [ "Action", "PS4", "PS5" ], "archived": false }, { "id": "220", "title": "Half-Life 2", "added": 1731173398617, "platform": 1, "uri": "https://store.steampowered.com/app/220", "tags": [ ], "archived": true }, { "id": "320", "title": "Half-Life 2: Deathmatch", "added": 1731173398617, "platform": 1, "uri": "https://store.steampowered.com/app/320", "tags": [ ], "archived": true }, { "id": "340", "title": "Half-Life 2: Lost Coast", "added": 1731173398617, "platform": 1, "uri": "https://store.steampowered.com/app/340", "tags": [ ], "archived": true }, { "id": "380", "title": "Half-Life 2: Episode One", "added": 1731173398617, "platform": 1, "uri": "https://store.steampowered.com/app/380", "tags": [ ], "archived": true }, { "id": "420", "title": "Half-Life 2: Episode Two", "added": 1731173398617, "platform": 1, "uri": "https://store.steampowered.com/app/420", "tags": [ ], "archived": true }, { "id": "1564571", "title": "Drug Dealin Sim 2024", "added": 1731173398851, "platform": 2, "uri": "https://b-render.itch.io/drug-dealin-simulator-2024", "tags": [ ], "archived": true }, { "id": "1628820", "title": "Small RPG", "added": 1731173398851, "platform": 2, "uri": "https://b-render.itch.io/small-rpg", "tags": [ ], "archived": true }, { "id": "2029854", "title": "Dummy Smasher", "added": 1731173398851, "platform": 2, "uri": "https://b-render.itch.io/dummy-smasher", "tags": [ ], "archived": true }, { "id": "2151604", "title": "Manuee's Adventure", "added": 1731173398851, "platform": 2, "uri": "https://jampley-dev.itch.io/manuees-adventure", "tags": [ ], "archived": true }, { "id": "2268482", "title": "Bone-ER-Clicker", "added": 1731173398851, "platform": 2, "uri": "https://b-render.itch.io/bone-clicker", "tags": [ ], "archived": true }, { "id": "2788150", "title": "Trespasser's Labyrinth", "added": 1731173398851, "platform": 2, "uri": "https://ethan-winters.itch.io/trespassers-labyrinth", "tags": [ ], "archived": true }, { "id": "2923706", "title": "Gold Digger", "added": 1731173398851, "platform": 2, "uri": "https://b-render.itch.io/gold-digger", "tags": [ ], "archived": true }, { "id": "3071310", "title": "Celestial Front", "added": 1731173398851, "platform": 2, "uri": "https://15joldersmat.itch.io/celestial-front", "tags": [ ], "archived": true } ]